audiopro.py
audiopro-0.0.2.dist-info/METADATA
audiopro-0.0.2.dist-info/WHEEL
audiopro-0.0.2.dist-info/entry_points.txt
audiopro-0.0.2.dist-info/top_level.txt
audiopro-0.0.2.dist-info/RECORD
